oemof/__init__.py
oemof/__main__.py
oemof/cli.py
oemof-1.0.dist-info/AUTHORS.rst
oemof-1.0.dist-info/LICENSE
oemof-1.0.dist-info/METADATA
oemof-1.0.dist-info/WHEEL
oemof-1.0.dist-info/top_level.txt
oemof-1.0.dist-info/RECORD
