Metadata-Version: 2.1
Name: oemof
Version: 1.0
Summary: Open Energy Modelling Framework - Python toolbox for energy system modelling and optimisation.
Home-page: https://github.com/oemof/oemof
Author: oemof developer group
Author-email: contact@oemof.org
License: MIT
Project-URL: Documentation, https://oemof.readthedocs.io/
Project-URL: Changelog, https://oemof.readthedocs.io/en/latest/changelog.html
Project-URL: Issue Tracker, https://github.com/oemof/oemof/issues
Classifier: Development Status :: 5 - Production/Stable
Classifier: Intended Audience :: Developers
Classifier: License :: OSI Approved :: MIT License
Classifier: Operating System :: Unix
Classifier: Operating System :: POSIX
Classifier: Operating System :: Microsoft :: Windows
Classifier: Programming Language :: Python
Classifier: Programming Language :: Python :: 3
Classifier: Programming Language :: Python :: 3.6
Classifier: Programming Language :: Python :: 3.7
Classifier: Programming Language :: Python :: 3.8
Classifier: Programming Language :: Python :: Implementation :: CPython
Classifier: Topic :: Utilities
Requires-Python: >=3.8
License-File: LICENSE
License-File: AUTHORS.rst
Requires-Dist: cydets
Requires-Dist: demandlib
Requires-Dist: dhnx
Requires-Dist: feedinlib
Requires-Dist: oemof.db
Requires-Dist: oemof.network
Requires-Dist: oemof.solph
Requires-Dist: oemof.tools
Requires-Dist: tespy
Requires-Dist: windpowerlib
